<?xml version="1.0" encoding="UTF-8" standalone="no"?>
<people>
    <person>
        <personId>1</personId>
        <firstName>John</firstName>
        <lastName>Doe</lastName>
        <mobile>123-456-7890</mobile>
        <email>john.doe@example.com</email>
        <pesel>12345678901</pesel>
    </person>
    <person>
        <personId>2</personId>
        <firstName>Jon</firstName>
        <lastName>Jones</lastName>
        <mobile>987-654-3210</mobile>
        <email>jon.jones@example.com</email>
        <pesel>98765432109</pesel>
    </person>
    <person>
        <personId>3</personId>
        <firstName>Bob</firstName>
        <lastName>Sapp</lastName>
        <mobile>555-123-4567</mobile>
        <email>bob.sapp@example.com</email>
        <pesel>55512345678</pesel>
    </person>
    <person>
        <personId>7</personId>
        <firstName>Johny</firstName>
        <lastName>Bravo</lastName>
        <mobile>333-123-4567</mobile>
        <email>Johny.Bravo@example.com</email>
        <pesel>55512345679</pesel>
    </person>
</people>